{"nodes": [{"id": "348_p0", "numId": 214257, "sex": "unknown", "birth_year": 1824, "banner_id": 2, "community_id": 348, "household_id": 187341}, {"id": "348_p1", "numId": 215539, "sex": "unknown", "birth_year": 1784, "banner_id": 2, "community_id": 348, "household_id": 187356}, {"id": "348_p2", "numId": 215891, "sex": "unknown", "birth_year": 1772, "banner_id": 2, "community_id": 348, "household_id": 187405}, {"id": "348_p3", "numId": 215892, "sex": "unknown", "birth_year": 1787, "banner_id": 2, "community_id": 348, "household_id": 187405}, {"id": "348_p4", "numId": 217285, "sex": "unknown", "birth_year": 1818, "banner_id": 2, "community_id": 348, "household_id": 187332}, {"id": "348_p5", "numId": 218039, "sex": "unknown", "birth_year": 1830, "banner_id": 2, "community_id": 348, "household_id": 187318}, {"id": "348_p6", "numId": 218044, "sex": "unknown", "birth_year": 1833, "banner_id": 2, "community_id": 348, "household_id": 187320}, {"id": "348_p7", "numId": 218063, "sex": "unknown", "birth_year": 1830, "banner_id": 2, "community_id": 348, "household_id": 187327}, {"id": "348_p8", "numId": 218073, "sex": "unknown", "birth_year": 1833, "banner_id": 2, "community_id": 348, "household_id": 187139}, {"id": "348_p9", "numId": 218079, "sex": "unknown", "birth_year": 1830, "banner_id": 2, "community_id": 348, "household_id": 187332}, {"id": "348_p10", "numId": 218080, "sex": "unknown", "birth_year": 1835, "banner_id": 2, "community_id": 348, "household_id": 187333}, {"id": "348_p11", "numId": 218088, "sex": "unknown", "birth_year": 1820, "banner_id": 2, "community_id": 348, "household_id": 187146}, {"id": "348_p12", "numId": 218090, "sex": "unknown", "birth_year": 1824, "banner_id": 2, "community_id": 348, "household_id": 187337}, {"id": "348_p13", "numId": 218096, "sex": "unknown", "birth_year": 1812, "banner_id": 2, "community_id": 348, "household_id": 187339}, {"id": "348_p14", "numId": 218098, "sex": "unknown", "birth_year": 1825, "banner_id": 2, "community_id": 348, "household_id": 187340}, {"id": "348_p15", "numId": 218101, "sex": "unknown", "birth_year": 1833, "banner_id": 2, "community_id": 348, "household_id": 187340}, {"id": "348_p16", "numId": 218117, "sex": "unknown", "birth_year": 1832, "banner_id": 2, "community_id": 348, "household_id": 187153}, {"id": "348_p17", "numId": 218118, "sex": "unknown", "birth_year": 1834, "banner_id": 2, "community_id": 348, "household_id": 187344}, {"id": "348_p18", "numId": 218120, "sex": "unknown", "birth_year": 1826, "banner_id": 2, "community_id": 348, "household_id": 187345}, {"id": "348_p19", "numId": 218136, "sex": "unknown", "birth_year": 1835, "banner_id": 2, "community_id": 348, "household_id": 187349}, {"id": "348_p20", "numId": 218138, "sex": "unknown", "birth_year": 1820, "banner_id": 2, "community_id": 348, "household_id": 187349}, {"id": "348_p21", "numId": 218149, "sex": "unknown", "birth_year": 1838, "banner_id": 2, "community_id": 348, "household_id": 187355}, {"id": "348_p22", "numId": 218169, "sex": "unknown", "birth_year": 1831, "banner_id": 2, "community_id": 348, "household_id": 187169}, {"id": "348_p23", "numId": 218220, "sex": "unknown", "birth_year": 1833, "banner_id": 2, "community_id": 348, "household_id": 187372}, {"id": "348_p24", "numId": 218227, "sex": "unknown", "birth_year": 1832, "banner_id": 2, "community_id": 348, "household_id": 187183}, {"id": "348_p25", "numId": 218238, "sex": "unknown", "birth_year": 1823, "banner_id": 2, "community_id": 348, "household_id": 187379}, {"id": "348_p26", "numId": 218241, "sex": "unknown", "birth_year": 1833, "banner_id": 2, "community_id": 348, "household_id": 187381}, {"id": "348_p27", "numId": 218250, "sex": "unknown", "birth_year": 1828, "banner_id": 2, "community_id": 348, "household_id": 187383}, {"id": "348_p28", "numId": 218286, "sex": "unknown", "birth_year": 1837, "banner_id": 2, "community_id": 348, "household_id": 187199}, {"id": "348_p29", "numId": 218289, "sex": "unknown", "birth_year": 1837, "banner_id": 2, "community_id": 348, "household_id": 187393}, {"id": "348_p30", "numId": 218297, "sex": "unknown", "birth_year": 1821, "banner_id": 2, "community_id": 348, "household_id": 187202}, {"id": "348_p31", "numId": 218300, "sex": "unknown", "birth_year": 1826, "banner_id": 2, "community_id": 348, "household_id": 187203}, {"id": "348_p32", "numId": 218301, "sex": "unknown", "birth_year": 1829, "banner_id": 2, "community_id": 348, "household_id": 187396}, {"id": "348_p33", "numId": 218317, "sex": "unknown", "birth_year": 1826, "banner_id": 2, "community_id": 348, "household_id": 187207}, {"id": "348_p34", "numId": 218318, "sex": "unknown", "birth_year": 1833, "banner_id": 2, "community_id": 348, "household_id": 187207}, {"id": "348_p35", "numId": 218323, "sex": "unknown", "birth_year": 1832, "banner_id": 2, "community_id": 348, "household_id": 187403}, {"id": "348_p36", "numId": 219995, "sex": "unknown", "birth_year": 1847, "banner_id": 2, "community_id": 348, "household_id": 187318}, {"id": "348_p37", "numId": 219997, "sex": "unknown", "birth_year": 1829, "banner_id": 2, "community_id": 348, "household_id": 187320}, {"id": "348_p38", "numId": 220002, "sex": "unknown", "birth_year": 1846, "banner_id": 2, "community_id": 348, "household_id": 187325}, {"id": "348_p39", "numId": 220010, "sex": "unknown", "birth_year": 1839, "banner_id": 2, "community_id": 348, "household_id": 187329}, {"id": "348_p40", "numId": 220011, "sex": "unknown", "birth_year": 1849, "banner_id": 2, "community_id": 348, "household_id": 187329}, {"id": "348_p41", "numId": 220012, "sex": "unknown", "birth_year": 1823, "banner_id": 2, "community_id": 348, "household_id": 187329}, {"id": "348_p42", "numId": 220013, "sex": "unknown", "birth_year": 1849, "banner_id": 2, "community_id": 348, "household_id": 187329}, {"id": "348_p43", "numId": 220017, "sex": "unknown", "birth_year": 1846, "banner_id": 2, "community_id": 348, "household_id": 187330}, {"id": "348_p44", "numId": 220022, "sex": "unknown", "birth_year": 1829, "banner_id": 2, "community_id": 348, "household_id": 187332}, {"id": "348_p45", "numId": 220027, "sex": "unknown", "birth_year": 1839, "banner_id": 2, "community_id": 348, "household_id": 187336}, {"id": "348_p46", "numId": 220030, "sex": "unknown", "birth_year": 1842, "banner_id": 2, "community_id": 348, "household_id": 187337}, {"id": "348_p47", "numId": 220031, "sex": "unknown", "birth_year": 1846, "banner_id": 2, "community_id": 348, "household_id": 187146}, {"id": "348_p48", "numId": 220032, "sex": "unknown", "birth_year": 1849, "banner_id": 2, "community_id": 348, "household_id": 187337}, {"id": "348_p49", "numId": 220035, "sex": "unknown", "birth_year": 1834, "banner_id": 2, "community_id": 348, "household_id": 187339}, {"id": "348_p50", "numId": 220036, "sex": "unknown", "birth_year": 1824, "banner_id": 2, "community_id": 348, "household_id": 187339}, {"id": "348_p51", "numId": 220040, "sex": "unknown", "birth_year": 1845, "banner_id": 2, "community_id": 348, "household_id": 187342}, {"id": "348_p52", "numId": 220044, "sex": "unknown", "birth_year": 1850, "banner_id": 2, "community_id": 348, "household_id": 187343}, {"id": "348_p53", "numId": 220047, "sex": "unknown", "birth_year": 1840, "banner_id": 2, "community_id": 348, "household_id": 187344}, {"id": "348_p54", "numId": 220057, "sex": "unknown", "birth_year": 1824, "banner_id": 2, "community_id": 348, "household_id": 187345}, {"id": "348_p55", "numId": 220058, "sex": "unknown", "birth_year": 1847, "banner_id": 2, "community_id": 348, "household_id": 187345}, {"id": "348_p56", "numId": 220061, "sex": "unknown", "birth_year": 1849, "banner_id": 2, "community_id": 348, "household_id": 187346}, {"id": "348_p57", "numId": 220065, "sex": "unknown", "birth_year": 1846, "banner_id": 2, "community_id": 348, "household_id": 187348}, {"id": "348_p58", "numId": 220068, "sex": "unknown", "birth_year": 1825, "banner_id": 2, "community_id": 348, "household_id": 187349}, {"id": "348_p59", "numId": 220069, "sex": "unknown", "birth_year": 1843, "banner_id": 2, "community_id": 348, "household_id": 187349}], "edges": [{"source": "348_p20", "target": "348_p59", "type": "r_fs"}, {"source": "348_p41", "target": "348_p42", "type": "r_ms"}, {"source": "348_p54", "target": "348_p55", "type": "r_ms"}, {"source": "348_p58", "target": "348_p59", "type": "r_ms"}, {"source": "348_p4", "target": "348_p9", "type": "r_sib"}, {"source": "348_p4", "target": "348_p44", "type": "r_sib"}, {"source": "348_p5", "target": "348_p36", "type": "r_sib"}, {"source": "348_p6", "target": "348_p37", "type": "r_sib"}, {"source": "348_p8", "target": "348_p43", "type": "r_sib"}, {"source": "348_p9", "target": "348_p4", "type": "r_sib"}, {"source": "348_p9", "target": "348_p44", "type": "r_sib"}, {"source": "348_p11", "target": "348_p12", "type": "r_sib"}, {"source": "348_p12", "target": "348_p11", "type": "r_sib"}, {"source": "348_p16", "target": "348_p17", "type": "r_sib"}, {"source": "348_p16", "target": "348_p53", "type": "r_sib"}, {"source": "348_p17", "target": "348_p16", "type": "r_sib"}, {"source": "348_p17", "target": "348_p53", "type": "r_sib"}, {"source": "348_p18", "target": "348_p54", "type": "r_sib"}, {"source": "348_p20", "target": "348_p58", "type": "r_sib"}, {"source": "348_p31", "target": "348_p32", "type": "r_sib"}, {"source": "348_p32", "target": "348_p31", "type": "r_sib"}, {"source": "348_p33", "target": "348_p34", "type": "r_sib"}, {"source": "348_p34", "target": "348_p33", "type": "r_sib"}, {"source": "348_p36", "target": "348_p5", "type": "r_sib"}, {"source": "348_p37", "target": "348_p6", "type": "r_sib"}, {"source": "348_p39", "target": "348_p40", "type": "r_sib"}, {"source": "348_p40", "target": "348_p39", "type": "r_sib"}, {"source": "348_p43", "target": "348_p8", "type": "r_sib"}, {"source": "348_p44", "target": "348_p4", "type": "r_sib"}, {"source": "348_p44", "target": "348_p9", "type": "r_sib"}, {"source": "348_p46", "target": "348_p47", "type": "r_sib"}, {"source": "348_p46", "target": "348_p48", "type": "r_sib"}, {"source": "348_p47", "target": "348_p46", "type": "r_sib"}, {"source": "348_p47", "target": "348_p48", "type": "r_sib"}, {"source": "348_p48", "target": "348_p46", "type": "r_sib"}, {"source": "348_p48", "target": "348_p47", "type": "r_sib"}, {"source": "348_p53", "target": "348_p16", "type": "r_sib"}, {"source": "348_p53", "target": "348_p17", "type": "r_sib"}, {"source": "348_p54", "target": "348_p18", "type": "r_sib"}, {"source": "348_p58", "target": "348_p20", "type": "r_sib"}]}