{"nodes": [{"id": "217_p0", "numId": 62561, "sex": "unknown", "birth_year": 1737, "banner_id": 0, "community_id": 217, "household_id": 70014}, {"id": "217_p1", "numId": 62563, "sex": "unknown", "birth_year": 1763, "banner_id": 0, "community_id": 217, "household_id": 71067}, {"id": "217_p2", "numId": 62565, "sex": "unknown", "birth_year": 1737, "banner_id": 0, "community_id": 217, "household_id": 70013}, {"id": "217_p3", "numId": 62566, "sex": "unknown", "birth_year": 1740, "banner_id": 0, "community_id": 217, "household_id": 71448}, {"id": "217_p4", "numId": 62573, "sex": "unknown", "birth_year": 1738, "banner_id": 0, "community_id": 217, "household_id": 69669}, {"id": "217_p5", "numId": 62574, "sex": "unknown", "birth_year": 1740, "banner_id": 0, "community_id": 217, "household_id": 70705}, {"id": "217_p6", "numId": 62575, "sex": "unknown", "birth_year": 1727, "banner_id": 0, "community_id": 217, "household_id": 70017}, {"id": "217_p7", "numId": 62577, "sex": "unknown", "birth_year": 1762, "banner_id": 0, "community_id": 217, "household_id": 70360}, {"id": "217_p8", "numId": 62579, "sex": "unknown", "birth_year": 1729, "banner_id": 0, "community_id": 217, "household_id": 71071}, {"id": "217_p9", "numId": 62581, "sex": "unknown", "birth_year": 1758, "banner_id": 0, "community_id": 217, "household_id": 74823}, {"id": "217_p10", "numId": 62582, "sex": "unknown", "birth_year": 1754, "banner_id": 0, "community_id": 217, "household_id": 73562}, {"id": "217_p11", "numId": 62585, "sex": "unknown", "birth_year": 1749, "banner_id": 0, "community_id": 217, "household_id": 71072}, {"id": "217_p12", "numId": 62588, "sex": "unknown", "birth_year": 1732, "banner_id": 0, "community_id": 217, "household_id": 70363}, {"id": "217_p13", "numId": 62589, "sex": "unknown", "birth_year": 1750, "banner_id": 0, "community_id": 217, "household_id": 70708}, {"id": "217_p14", "numId": 62590, "sex": "unknown", "birth_year": 1760, "banner_id": 0, "community_id": 217, "household_id": 72774}, {"id": "217_p15", "numId": 62594, "sex": "unknown", "birth_year": 1710, "banner_id": 0, "community_id": 217, "household_id": 69308}, {"id": "217_p16", "numId": 62595, "sex": "unknown", "birth_year": 1747, "banner_id": 0, "community_id": 217, "household_id": 70346}, {"id": "217_p17", "numId": 62596, "sex": "unknown", "birth_year": 1748, "banner_id": 0, "community_id": 217, "household_id": 70693}, {"id": "217_p18", "numId": 62598, "sex": "unknown", "birth_year": 1725, "banner_id": 0, "community_id": 217, "household_id": 70332}, {"id": "217_p19", "numId": 62600, "sex": "unknown", "birth_year": 1747, "banner_id": 0, "community_id": 217, "household_id": 71043}, {"id": "217_p20", "numId": 62601, "sex": "unknown", "birth_year": 1745, "banner_id": 0, "community_id": 217, "household_id": 71811}, {"id": "217_p21", "numId": 62603, "sex": "unknown", "birth_year": 1753, "banner_id": 0, "community_id": 217, "household_id": 72359}, {"id": "217_p22", "numId": 62604, "sex": "unknown", "birth_year": 1758, "banner_id": 0, "community_id": 217, "household_id": 72199}, {"id": "217_p23", "numId": 62608, "sex": "unknown", "birth_year": 1731, "banner_id": 0, "community_id": 217, "household_id": 69298}, {"id": "217_p24", "numId": 62609, "sex": "unknown", "birth_year": 1751, "banner_id": 0, "community_id": 217, "household_id": 70681}, {"id": "217_p25", "numId": 62610, "sex": "unknown", "birth_year": 1752, "banner_id": 0, "community_id": 217, "household_id": 71813}, {"id": "217_p26", "numId": 62612, "sex": "unknown", "birth_year": 1737, "banner_id": 0, "community_id": 217, "household_id": 71425}, {"id": "217_p27", "numId": 62614, "sex": "unknown", "birth_year": 1739, "banner_id": 0, "community_id": 217, "household_id": 71042}, {"id": "217_p28", "numId": 62615, "sex": "unknown", "birth_year": 1763, "banner_id": 0, "community_id": 217, "household_id": 71042}, {"id": "217_p29", "numId": 62618, "sex": "unknown", "birth_year": 1730, "banner_id": 0, "community_id": 217, "household_id": 69002}, {"id": "217_p30", "numId": 62619, "sex": "unknown", "birth_year": 1756, "banner_id": 0, "community_id": 217, "household_id": 71046}, {"id": "217_p31", "numId": 62622, "sex": "unknown", "birth_year": 1731, "banner_id": 0, "community_id": 217, "household_id": 69300}, {"id": "217_p32", "numId": 62623, "sex": "unknown", "birth_year": 1732, "banner_id": 0, "community_id": 217, "household_id": 70335}, {"id": "217_p33", "numId": 62625, "sex": "unknown", "birth_year": 1745, "banner_id": 0, "community_id": 217, "household_id": 69300}, {"id": "217_p34", "numId": 62626, "sex": "unknown", "birth_year": 1755, "banner_id": 0, "community_id": 217, "household_id": 71430}, {"id": "217_p35", "numId": 62632, "sex": "unknown", "birth_year": 1738, "banner_id": 0, "community_id": 217, "household_id": 71048}, {"id": "217_p36", "numId": 62637, "sex": "unknown", "birth_year": 1729, "banner_id": 0, "community_id": 217, "household_id": 70337}, {"id": "217_p37", "numId": 62638, "sex": "unknown", "birth_year": 1751, "banner_id": 0, "community_id": 217, "household_id": 70337}, {"id": "217_p38", "numId": 62639, "sex": "unknown", "birth_year": 1752, "banner_id": 0, "community_id": 217, "household_id": 71818}, {"id": "217_p39", "numId": 62640, "sex": "unknown", "birth_year": 1752, "banner_id": 0, "community_id": 217, "household_id": 71818}, {"id": "217_p40", "numId": 62647, "sex": "unknown", "birth_year": 1747, "banner_id": 0, "community_id": 217, "household_id": 70694}, {"id": "217_p41", "numId": 62648, "sex": "unknown", "birth_year": 1736, "banner_id": 0, "community_id": 217, "household_id": 70695}, {"id": "217_p42", "numId": 62649, "sex": "unknown", "birth_year": 1739, "banner_id": 0, "community_id": 217, "household_id": 71059}, {"id": "217_p43", "numId": 62652, "sex": "unknown", "birth_year": 1740, "banner_id": 0, "community_id": 217, "household_id": 70695}, {"id": "217_p44", "numId": 62653, "sex": "unknown", "birth_year": 1749, "banner_id": 0, "community_id": 217, "household_id": 71059}, {"id": "217_p45", "numId": 62656, "sex": "unknown", "birth_year": 1733, "banner_id": 0, "community_id": 217, "household_id": 71060}, {"id": "217_p46", "numId": 62660, "sex": "unknown", "birth_year": 1741, "banner_id": 0, "community_id": 217, "household_id": 70697}, {"id": "217_p47", "numId": 62661, "sex": "unknown", "birth_year": 1741, "banner_id": 0, "community_id": 217, "household_id": 70697}, {"id": "217_p48", "numId": 62662, "sex": "unknown", "birth_year": 1763, "banner_id": 0, "community_id": 217, "household_id": 73146}, {"id": "217_p49", "numId": 62663, "sex": "unknown", "birth_year": 1766, "banner_id": 0, "community_id": 217, "household_id": 73146}, {"id": "217_p50", "numId": 62664, "sex": "unknown", "birth_year": 1752, "banner_id": 0, "community_id": 217, "household_id": 69659}, {"id": "217_p51", "numId": 62670, "sex": "unknown", "birth_year": 1752, "banner_id": 0, "community_id": 217, "household_id": 71063}, {"id": "217_p52", "numId": 62671, "sex": "unknown", "birth_year": 1730, "banner_id": 0, "community_id": 217, "household_id": 70700}, {"id": "217_p53", "numId": 62672, "sex": "unknown", "birth_year": 1743, "banner_id": 0, "community_id": 217, "household_id": 71446}, {"id": "217_p54", "numId": 62677, "sex": "unknown", "birth_year": 1722, "banner_id": 0, "community_id": 217, "household_id": 70011}, {"id": "217_p55", "numId": 62682, "sex": "unknown", "birth_year": 1733, "banner_id": 0, "community_id": 217, "household_id": 70701}, {"id": "217_p56", "numId": 62686, "sex": "unknown", "birth_year": 1724, "banner_id": 0, "community_id": 217, "household_id": 70355}, {"id": "217_p57", "numId": 62690, "sex": "unknown", "birth_year": 1739, "banner_id": 0, "community_id": 217, "household_id": 73135}, {"id": "217_p58", "numId": 62692, "sex": "unknown", "birth_year": 1741, "banner_id": 0, "community_id": 217, "household_id": 69303}, {"id": "217_p59", "numId": 62693, "sex": "unknown", "birth_year": 1738, "banner_id": 0, "community_id": 217, "household_id": 69303}], "edges": [{"source": "217_p16", "target": "217_p17", "type": "r_hw"}, {"source": "217_p19", "target": "217_p20", "type": "r_hw"}, {"source": "217_p26", "target": "217_p27", "type": "r_hw"}, {"source": "217_p31", "target": "217_p32", "type": "r_hw"}, {"source": "217_p38", "target": "217_p39", "type": "r_hw"}, {"source": "217_p41", "target": "217_p42", "type": "r_hw"}, {"source": "217_p43", "target": "217_p44", "type": "r_hw"}, {"source": "217_p46", "target": "217_p47", "type": "r_hw"}, {"source": "217_p52", "target": "217_p53", "type": "r_hw"}, {"source": "217_p57", "target": "217_p58", "type": "r_hw"}, {"source": "217_p6", "target": "217_p7", "type": "r_fs"}, {"source": "217_p26", "target": "217_p28", "type": "r_fs"}, {"source": "217_p31", "target": "217_p33", "type": "r_fs"}, {"source": "217_p31", "target": "217_p34", "type": "r_fs"}, {"source": "217_p46", "target": "217_p48", "type": "r_fs"}, {"source": "217_p46", "target": "217_p49", "type": "r_fs"}, {"source": "217_p0", "target": "217_p1", "type": "r_ms"}, {"source": "217_p8", "target": "217_p9", "type": "r_ms"}, {"source": "217_p8", "target": "217_p10", "type": "r_ms"}, {"source": "217_p12", "target": "217_p13", "type": "r_ms"}, {"source": "217_p12", "target": "217_p14", "type": "r_ms"}, {"source": "217_p15", "target": "217_p16", "type": "r_ms"}, {"source": "217_p15", "target": "217_p17", "type": "r_ms"}, {"source": "217_p18", "target": "217_p19", "type": "r_ms"}, {"source": "217_p18", "target": "217_p20", "type": "r_ms"}, {"source": "217_p18", "target": "217_p21", "type": "r_ms"}, {"source": "217_p18", "target": "217_p22", "type": "r_ms"}, {"source": "217_p23", "target": "217_p24", "type": "r_ms"}, {"source": "217_p23", "target": "217_p25", "type": "r_ms"}, {"source": "217_p27", "target": "217_p28", "type": "r_ms"}, {"source": "217_p29", "target": "217_p30", "type": "r_ms"}, {"source": "217_p32", "target": "217_p33", "type": "r_ms"}, {"source": "217_p32", "target": "217_p34", "type": "r_ms"}, {"source": "217_p36", "target": "217_p37", "type": "r_ms"}, {"source": "217_p36", "target": "217_p38", "type": "r_ms"}, {"source": "217_p36", "target": "217_p39", "type": "r_ms"}, {"source": "217_p47", "target": "217_p48", "type": "r_ms"}, {"source": "217_p47", "target": "217_p49", "type": "r_ms"}, {"source": "217_p0", "target": "217_p2", "type": "r_sib"}, {"source": "217_p0", "target": "217_p3", "type": "r_sib"}, {"source": "217_p2", "target": "217_p0", "type": "r_sib"}, {"source": "217_p2", "target": "217_p3", "type": "r_sib"}, {"source": "217_p3", "target": "217_p0", "type": "r_sib"}, {"source": "217_p3", "target": "217_p2", "type": "r_sib"}, {"source": "217_p4", "target": "217_p5", "type": "r_sib"}, {"source": "217_p4", "target": "217_p6", "type": "r_sib"}, {"source": "217_p5", "target": "217_p4", "type": "r_sib"}, {"source": "217_p5", "target": "217_p6", "type": "r_sib"}, {"source": "217_p6", "target": "217_p4", "type": "r_sib"}, {"source": "217_p6", "target": "217_p5", "type": "r_sib"}, {"source": "217_p9", "target": "217_p10", "type": "r_sib"}, {"source": "217_p10", "target": "217_p9", "type": "r_sib"}, {"source": "217_p13", "target": "217_p14", "type": "r_sib"}, {"source": "217_p14", "target": "217_p13", "type": "r_sib"}, {"source": "217_p16", "target": "217_p17", "type": "r_sib"}, {"source": "217_p17", "target": "217_p16", "type": "r_sib"}, {"source": "217_p19", "target": "217_p20", "type": "r_sib"}, {"source": "217_p19", "target": "217_p21", "type": "r_sib"}, {"source": "217_p19", "target": "217_p22", "type": "r_sib"}, {"source": "217_p20", "target": "217_p19", "type": "r_sib"}, {"source": "217_p20", "target": "217_p21", "type": "r_sib"}, {"source": "217_p20", "target": "217_p22", "type": "r_sib"}, {"source": "217_p21", "target": "217_p19", "type": "r_sib"}, {"source": "217_p21", "target": "217_p20", "type": "r_sib"}, {"source": "217_p21", "target": "217_p22", "type": "r_sib"}, {"source": "217_p22", "target": "217_p19", "type": "r_sib"}, {"source": "217_p22", "target": "217_p20", "type": "r_sib"}, {"source": "217_p22", "target": "217_p21", "type": "r_sib"}, {"source": "217_p24", "target": "217_p25", "type": "r_sib"}, {"source": "217_p25", "target": "217_p24", "type": "r_sib"}, {"source": "217_p33", "target": "217_p34", "type": "r_sib"}, {"source": "217_p34", "target": "217_p33", "type": "r_sib"}, {"source": "217_p36", "target": "217_p37", "type": "r_sib"}, {"source": "217_p36", "target": "217_p38", "type": "r_sib"}, {"source": "217_p36", "target": "217_p39", "type": "r_sib"}, {"source": "217_p37", "target": "217_p36", "type": "r_sib"}, {"source": "217_p37", "target": "217_p38", "type": "r_sib"}, {"source": "217_p37", "target": "217_p39", "type": "r_sib"}, {"source": "217_p38", "target": "217_p36", "type": "r_sib"}, {"source": "217_p38", "target": "217_p37", "type": "r_sib"}, {"source": "217_p38", "target": "217_p39", "type": "r_sib"}, {"source": "217_p39", "target": "217_p36", "type": "r_sib"}, {"source": "217_p39", "target": "217_p37", "type": "r_sib"}, {"source": "217_p39", "target": "217_p38", "type": "r_sib"}, {"source": "217_p46", "target": "217_p47", "type": "r_sib"}, {"source": "217_p46", "target": "217_p50", "type": "r_sib"}, {"source": "217_p47", "target": "217_p46", "type": "r_sib"}, {"source": "217_p47", "target": "217_p50", "type": "r_sib"}, {"source": "217_p48", "target": "217_p49", "type": "r_sib"}, {"source": "217_p49", "target": "217_p48", "type": "r_sib"}, {"source": "217_p50", "target": "217_p46", "type": "r_sib"}, {"source": "217_p50", "target": "217_p47", "type": "r_sib"}, {"source": "217_p54", "target": "217_p55", "type": "r_sib"}, {"source": "217_p55", "target": "217_p54", "type": "r_sib"}, {"source": "217_p57", "target": "217_p58", "type": "r_sib"}, {"source": "217_p57", "target": "217_p59", "type": "r_sib"}, {"source": "217_p58", "target": "217_p57", "type": "r_sib"}, {"source": "217_p58", "target": "217_p59", "type": "r_sib"}, {"source": "217_p59", "target": "217_p57", "type": "r_sib"}, {"source": "217_p59", "target": "217_p58", "type": "r_sib"}]}